punch_clock.py
personal_punch_clock-1.0.0.dist-info/LICENSE
personal_punch_clock-1.0.0.dist-info/METADATA
personal_punch_clock-1.0.0.dist-info/WHEEL
personal_punch_clock-1.0.0.dist-info/entry_points.txt
personal_punch_clock-1.0.0.dist-info/top_level.txt
personal_punch_clock-1.0.0.dist-info/RECORD
