Metadata-Version: 2.1
Name: personal-punch-clock
Version: 1.0.0
Summary: A bare-bones command-line punch clock
Author: Nickolas Wilson
Project-URL: Repository, https://github.com/nickolasjwilson/personal-punch-clock
Keywords: punch clock,time clock
Classifier: Programming Language :: Python :: 3
Classifier: License :: OSI Approved :: Apache Software License
License-File: LICENSE
Requires-Dist: pandas ~=2.2
Provides-Extra: dev
